evbus_pika/conf.py
evbus_pika/version.py
evbus_pika/ingress/pika.py
evbus_pika-5.0.0.dist-info/LICENSE
evbus_pika-5.0.0.dist-info/METADATA
evbus_pika-5.0.0.dist-info/WHEEL
evbus_pika-5.0.0.dist-info/top_level.txt
evbus_pika-5.0.0.dist-info/RECORD
