Metadata-Version: 2.1
Name: evbus-pika
Version: 5.0.0
Summary: app-merge component for pop-evbus
Home-page: https://gitlab.com/vmware/idem/evbus-pika
Author: Tyler Johnson
Author-email: tyjohnson@vmware.com
License: UNKNOWN
Platform: UNKNOWN
Classifier: Environment :: Console
Classifier: Intended Audience :: Developers
Classifier: Intended Audience :: Information Technology
Classifier: Intended Audience :: System Administrators
Classifier: Operating System :: OS Independent
Classifier: Programming Language :: Python
Classifier: Programming Language :: Python :: 3.8
Classifier: Programming Language :: Python :: 3.9
Classifier: Programming Language :: Python :: 3.10
Classifier: Programming Language :: Python :: 3.11
Classifier: Development Status :: 5 - Production/Stable
Requires-Python: >=3.8
License-File: LICENSE
Requires-Dist: pop-evbus (>=6.1.0)
Requires-Dist: aio-pika
Requires-Dist: acct (>=6.4.2)
Requires-Dist: pop (>=21)
